sftpovw/__init__.py
sftpovw/fs.py
sftpovw/main.py
sftpovw/version.py
sftpovw-0.1.dev1.dist-info/licenses/LICENSE
sftpovw-0.1.dev1.dist-info/METADATA
sftpovw-0.1.dev1.dist-info/WHEEL
sftpovw-0.1.dev1.dist-info/entry_points.txt
sftpovw-0.1.dev1.dist-info/top_level.txt
sftpovw-0.1.dev1.dist-info/RECORD
