Metadata-Version: 2.4
Name: sftpovw
Version: 0.1.dev1
Summary: write safer, sftp
Home-page: https://github.com/wtnb75/relppy
Author: Watanabe Takashi
Author-email: wtnb75@gmail.com
License: MIT
Classifier: Development Status :: 3 - Alpha
Classifier: Intended Audience :: Developers
Classifier: License :: OSI Approved :: MIT License
Classifier: Topic :: System :: Networking
Classifier: Programming Language :: Python :: 3
License-File: LICENSE
Requires-Dist: paramiko
Requires-Dist: click
Dynamic: license-file
Dynamic: requires-dist
